<?xml version="1.0" encoding="UTF-8"?><cycle title="Fenêtre sur les collections"><enTete><xTitreCycle>Fenêtre sur les collections&#xA;</xTitreCycle><action><actionSection title="Séances présentées"><xActionSectionTitre>Séances présentées&#xA;</xActionSectionTitre><xActionItem><xActionFilms>Le Pont-Neuf / Arc de triomphe / Place Bellecour / Colleurs d'affiches / Danse serpentine, I / Escamotage d'une dame chez Robert-Houdin / Les Bouteilles / Peinture à l'envers / Le Squelette joyeux / Thiers, Mac-Mahon, Grévy, Carnot, Félix Faure / Prestidigitateur, I / Prestidigitateur, II / Le Prestidigitateur au café / Le Château hanté / Pierrot et la flûte enchantée / Le Repas fantastique / Les Poupées / Tentation de Saint-Antoine / Un prêté pour un rendu / Pierrot et la mouche / Jongleur au ballon / Assiettes tournantes / Serpent / Chapeaux à transformation / Écriture à l'envers</xActionFilms>, par Frédéric Tabet&#xA;</xActionItem><xActionDateHeure>►&#xA0;<xGrey>Ve 03 avr 18h30&#xA;</xGrey></xActionDateHeure><xActionItem><xActionFilms>L'Illusionniste</xActionFilms>, par Frédéric Tabet&#xA;</xActionItem><xActionDateHeure>►&#xA0;<xGrey>Ve 03 avr 20h30&#xA;</xGrey></xActionDateHeure></actionSection></action></enTete><sousCycle title="Magiciens pris sur le vif : Velle, Trewey, Méliès"><xTitreSousCycle>Magiciens pris sur le vif&#xA0;: Velle, Trewey, Méliès&#xA;</xTitreSousCycle><xTexteSousCycle>Des vues Lumière à <xTexteSousCycle_Italic>L’Illusionniste</xTexteSousCycle_Italic> de Neil Burger, le cinéma n’a cessé de capter l’animation de la ville&#xA0;: rues, foires, cafés-concerts et cabarets. À côté des grands effets scéniques du théâtre, Frédéric Tabet (directeur de l’École nationale supérieure d’audiovisuel et artiste magicien) propose une séance-spectacle qui explore les formes légères de l’illusion et le destin des artistes itinérants. Pensées en écho de part et d’autre du XX<xSup>e</xSup> siècle, les deux séances interrogent ce que les vues animées révèlent du spectacle magique.&#xA;</xTexteSousCycle><programme title="[Sans titre] (25 films)"><xTitre_First>Le Pont-Neuf&#xA;</xTitre_First><xRealisateurs>Anonyme&#xA;</xRealisateurs><xInfosTechniques>France. 1897&#xA;</xInfosTechniques><xTitre_VSpaceMin>Arc de triomphe&#xA;</xTitre_VSpaceMin><xRealisateurs>Anonyme&#xA;</xRealisateurs><xInfosTechniques>France. 1896. 1’. 35&#xA0;mm&#xA;</xInfosTechniques><xTitre_VSpaceMin>Place Bellecour&#xA;</xTitre_VSpaceMin><xRealisateurs>Louis Lumière&#xA;</xRealisateurs><xInfosTechniques>France. 1896. 1’. 35&#xA0;mm&#xA;</xInfosTechniques><xTitre_VSpaceMin>Colleurs d’affiches&#xA;</xTitre_VSpaceMin><xRealisateurs>Georges Hatot, Gaston Breteau&#xA;</xRealisateurs><xInfosTechniques>France. 1897. 1’. 35&#xA0;mm&#xA;</xInfosTechniques><xTitre_VSpaceMin>Danse serpentine, I&#xA;</xTitre_VSpaceMin><xRealisateurs>Anonyme&#xA;</xRealisateurs><xInfosTechniques>France. 1897. 1’. 35&#xA0;mm&#xA;</xInfosTechniques><xTitre_VSpaceMin>Escamotage d’une dame chez Robert-Houdin&#xA;</xTitre_VSpaceMin><xRealisateurs>Georges Méliès&#xA;</xRealisateurs><xInfosTechniques>France. 1896. 2’. DCP. <xVersionRestauree>Version restaurée&#xA;</xVersionRestauree></xInfosTechniques><xTitre_VSpaceMin>Les Bouteilles&#xA;</xTitre_VSpaceMin><xRealisateurs>Anonyme&#xA;</xRealisateurs><xInfosTechniques>France. 1899. 1’. 35&#xA0;mm&#xA;</xInfosTechniques><xTitre_VSpaceMin>Peinture à l’envers&#xA;</xTitre_VSpaceMin><xRealisateurs>Anonyme&#xA;</xRealisateurs><xInfosTechniques>France. 1897. 1’. 35&#xA0;mm&#xA;</xInfosTechniques><xTitre_VSpaceMin>Le Squelette joyeux&#xA;</xTitre_VSpaceMin><xRealisateurs>Louis Lumière&#xA;</xRealisateurs><xInfosTechniques>France. 1898. 1’. 35&#xA0;mm&#xA;</xInfosTechniques><xTitre_VSpaceMin>Thiers, Mac-Mahon, Grévy, Carnot, Félix Faure&#xA;</xTitre_VSpaceMin><xRealisateurs>Anonyme&#xA;</xRealisateurs><xInfosTechniques>France. 1898. 1’. 35&#xA0;mm&#xA;</xInfosTechniques><xTitre_VSpaceMin>Prestidigitateur, I&#xA;</xTitre_VSpaceMin><xRealisateurs>Anonyme&#xA;</xRealisateurs><xInfosTechniques>France. 1897. 1’. 35&#xA0;mm&#xA;</xInfosTechniques><xTitre_VSpaceMin>Prestidigitateur, II&#xA;</xTitre_VSpaceMin><xRealisateurs>Anonyme&#xA;</xRealisateurs><xInfosTechniques>France. 1897. 1’. 35&#xA0;mm&#xA;</xInfosTechniques><xTitre_VSpaceMin>Le Prestidigitateur au café&#xA;</xTitre_VSpaceMin><xRealisateurs>Gaston Velle&#xA;</xRealisateurs><xInfosTechniques>France. 1903. 2’. 35&#xA0;mm&#xA;</xInfosTechniques><xTitre_VSpaceMin>Le Château hanté&#xA;</xTitre_VSpaceMin><xRealisateurs>Gaston Velle&#xA;</xRealisateurs><xInfosTechniques>France. 1903. 1’. 35&#xA0;mm&#xA;</xInfosTechniques><xTitre_VSpaceMin>Pierrot et la flûte enchantée&#xA;</xTitre_VSpaceMin><xRealisateurs>Gaston Velle&#xA;</xRealisateurs><xInfosTechniques>France. 1903. 1’. 35&#xA0;mm&#xA;</xInfosTechniques><xTitre_VSpaceMin>Le Repas fantastique&#xA;</xTitre_VSpaceMin><xRealisateurs>Gaston Velle&#xA;</xRealisateurs><xInfosTechniques>France. 1903. 2’. 35&#xA0;mm&#xA;</xInfosTechniques><xTitre_VSpaceMin>Les Poupées&#xA;</xTitre_VSpaceMin><xRealisateurs>Gaston Velle&#xA;</xRealisateurs><xInfosTechniques>France. 1903. 1’. 35&#xA0;mm&#xA;</xInfosTechniques><xTitre_VSpaceMin>Tentation de Saint-Antoine&#xA;</xTitre_VSpaceMin><xRealisateurs>Gaston Velle&#xA;</xRealisateurs><xInfosTechniques>France. 1903. 2’. 35&#xA0;mm&#xA;</xInfosTechniques><xTitre_VSpaceMin>Un prêté pour un rendu&#xA;</xTitre_VSpaceMin><xRealisateurs>Louis Lumière&#xA;</xRealisateurs><xInfosTechniques>France. 1896. 1’. 35&#xA0;mm&#xA;</xInfosTechniques><xTitre_VSpaceMin>Pierrot et la mouche&#xA;</xTitre_VSpaceMin><xRealisateurs>Louis Lumière&#xA;</xRealisateurs><xInfosTechniques>France. 1989. 1’. 35&#xA0;mm&#xA;</xInfosTechniques><xTitre_VSpaceMin>Jongleur au ballon&#xA;</xTitre_VSpaceMin><xRealisateurs>Louis Lumière&#xA;</xRealisateurs><xInfosTechniques>France. 1897. 1’. 35&#xA0;mm&#xA;</xInfosTechniques><xTitre_VSpaceMin>Assiettes tournantes&#xA;</xTitre_VSpaceMin><xRealisateurs>Louis Lumière&#xA;</xRealisateurs><xInfosTechniques>France. 1896. 1’. 35&#xA0;mm&#xA;</xInfosTechniques><xTitre_VSpaceMin>Serpent&#xA;</xTitre_VSpaceMin><xRealisateurs>Louis Lumière&#xA;</xRealisateurs><xInfosTechniques>France. 1896. 1’. 35&#xA0;mm&#xA;</xInfosTechniques><xTitre_VSpaceMin>Chapeaux à transformation&#xA;</xTitre_VSpaceMin><xRealisateurs>Louis Lumière&#xA;</xRealisateurs><xInfosTechniques>France. 1896. 1’. 35&#xA0;mm&#xA;</xInfosTechniques><xTitre_VSpaceMin>Écriture à l’envers&#xA;</xTitre_VSpaceMin><xRealisateurs>Louis Lumière&#xA;</xRealisateurs><xInfosTechniques>France. 1896. 1’. 35&#xA0;mm&#xA;</xInfosTechniques><xInfosSeance_VSpace>Ve 03 avr 18h30&#x202F;-&#x202F;JE&#xA0;<xMention>Accompagnement musical par Ignacio Plaza. Séance présentée par Frédéric Tabet&#xA;</xMention></xInfosSeance_VSpace></programme><film title="L'Illusionniste"><xTitre>L’Illusionniste&#xA;</xTitre><xTitreVo>(The Illusionist)&#xA;</xTitreVo><xRealisateurs>Neil Burger&#xA;</xRealisateurs><xInfosTechniques>États-Unis-République tchèque. 2005. 110’. 35&#xA0;mm. VOSTF&#xA;</xInfosTechniques><xInfosSeance>Ve 03 avr 20h30&#x202F;-&#x202F;JE&#xA0;<xMention>Séance présentée par Frédéric Tabet&#xA;</xMention></xInfosSeance></film></sousCycle><sousCycle title="Contrechamp d'Orient"><xTitreSousCycle>Contrechamp d’Orient&#xA;</xTitreSousCycle><xTexteSousCycle>Depuis les premières prises de vues, le cinématographe s’est attaché à restituer un spectacle conforme à ce qu’il voyait ou imaginait. À l’heure des empires coloniaux, les opérateurs ont fait entrer dans leur champ différentes formes d’altérité, imprégnées de fantasmes exotiques et orientalistes. Du récit colonial «&#xA0;civilisateur&#xA0;» sur fond de pacification à la fin du XIX<xSup>e</xSup> siècle aux bombardements déguisés en «&#xA0;frappes préventives&#xA0;», l’Occident s’est représenté conquérant, victorieux et vertueux, occultant le point de vue oriental. En 1991, lors de la première guerre du Golfe, Serge Daney analyse le dispositif télévisuel&#xA0;: de ce conflit montré en direct, on ne voit rien. Le contrechamp irakien est absent, ce qui crée un «&#xA0;déficit d’imagination&#xA0;». Voir et montrer ce contrechamp sont alors «&#xA0;devenus comme des actes de résistance&#xA0;».&#xA;</xTexteSousCycle><programme title="[Sans titre] (3 films)"><xTitre_First>Marché d’esclaves en Orient&#xA;</xTitre_First><xRealisateurs>Anonyme&#xA;</xRealisateurs><xInfosTechniques>France. 1897. 1’. 35&#xA0;mm&#xA;</xInfosTechniques><xTitre_VSpaceMin>Le Temps qu’il reste (bande-annonce)&#xA;</xTitre_VSpaceMin><xRealisateurs>Elia Suleiman&#xA;</xRealisateurs><xInfosTechniques>France-Palestine-Italie-Belgique-Grande-Bretagne. 2009. 2’. 35&#xA0;mm. VOSTF&#xA;</xInfosTechniques><xTitre_VSpaceMin>La Guerre du Golfe... et après&#xA;</xTitre_VSpaceMin><xTitreVo>(Harb el khalij... wa baad)&#xA;</xTitreVo><xRealisateurs>Nouri Bouzid, Néjia Ben Mabrouk, Borhane Alaouié, Elia Suleiman, Mustapha Derkaoui&#xA;</xRealisateurs><xInfosTechniques>Tunisie. 1991. 103’. 35&#xA0;mm. VOSTF&#xA;</xInfosTechniques><xInfosSeance_VSpace>Ve 08 mai 18h30&#x202F;-&#x202F;JE&#xA;</xInfosSeance_VSpace></programme><programme title="[Sans titre] (2 films)"><xTitre>La Frontière&#xA;</xTitre><xTitreVo>(Al-Hodoud)&#xA;</xTitreVo><xRealisateurs>Duraid Lahham&#xA;</xRealisateurs><xInfosTechniques>Syrie. 1984. 8’. DCP. VOSTF&#xA;</xInfosTechniques><xGenerique>Avec Duraid&#xA0;Lahham, Raghda, Hani&#xA0;Al&#x2011;Rumani.&#xA;</xGenerique><xTitre_VSpaceMin>Chronique d’une disparition&#xA;</xTitre_VSpaceMin><xTitreVo>(Segell ikhtifa)&#xA;</xTitreVo><xRealisateurs>Elia Suleiman&#xA;</xRealisateurs><xInfosTechniques>Israël-États-Unis-Allemagne. 1996. 87’. 35&#xA0;mm. VOSTF&#xA;</xInfosTechniques><xGenerique>Avec Elia&#xA0;Suleiman, Ula&#xA0;Tabari.&#xA;</xGenerique><xInfosSeance_VSpace>Ve 08 mai 21h00&#x202F;-&#x202F;JE&#xA;</xInfosSeance_VSpace></programme></sousCycle></cycle>