{
  "data": [
    {
      "titreSousCycle": "Les films",
      "tri": 2,
      "items": [
        {
          "idSeance": 208722,
          "ordre": 1,
          "dateHeure": "2026-03-18T17:30:00",
          "idSalle": [
            "GF",
            "Georges Franju"
          ],
          "dureeSeance": 120,
          "idCategorie": 4084,
          "idEvenement": 34833,
          "typeEvenement": 13,
          "idFilm": 50469,
          "art": "L'",
          "titre": "Atlantide",
          "realisateurs": "Georg Wilhelm Pabst",
          "annee": 1932,
          "pays": "France-Allemagne",
          "duree": 89,
          "version": "",
          "format": "DCP",
          "generique": [
            "Pierre Blanchar",
            "Jean Angelo",
            "Brigitte Helm",
            "Tela-Tchaï"
          ],
          "adaptation": "D'après le roman _L'Atlantide_ de Pierre Benoit.",
          "textes": [
            {
              "typeTexte": 1000,
              "texte": "Deux officiers explorent le désert à la recherche de l'Atlantide disparue et se réveillent dans le palais de la reine Antinéa. Brigitte Helm, la star de _Metropolis_, en idéal fantasmé, face à Pierre Blanchar, habité par la fièvre. Un mirage, une hallucination onirique, entre ombres et lumière : Pabst adapte le roman de Pierre Benoit et met en scène la folie humaine."
            }
          ]
        },
        {
          "idSeance": 208653,
          "ordre": 1,
          "dateHeure": "2026-03-27T16:30:00",
          "idSalle": [
            "GF",
            "Georges Franju"
          ],
          "dureeSeance": 120,
          "idCategorie": 4084,
          "idEvenement": 34829,
          "typeEvenement": 13,
          "idFilm": 33172,
          "art": "La",
          "titre": "Dame du vendredi",
          "titreVo": "His Girl Friday",
          "realisateurs": "Howard Hawks",
          "annee": 1940,
          "pays": "États-Unis",
          "duree": 92,
          "version": "VOSTF",
          "format": "DCP",
          "generique": [
            "Cary Grant",
            "Rosalind Russell",
            "Ralph Bellamy"
          ],
          "adaptation": "D'après la pièce _The Front Page_ de Ben Hecht et Charles MacArthur.",
          "textes": [
            {
              "typeTexte": 1000,
              "texte": "Une brillante comédie de mœurs, chef-d'œuvre du timing comique. Dialogues hilarants et joutes verbales se succèdent à un débit de mitraillette, et Hawks compose un hommage au cinéma muet, doublé d'une critique des médias. En pleine guerre des sexes, il révèle la piquante Rosalind Russell, qui tient tête à Cary Grant et Ralph Bellamy."
            }
          ]
        },
        {
          "idSeance": 208723,
          "ordre": 1,
          "dateHeure": "2026-03-19T16:00:00",
          "idSalle": [
            "GF",
            "Georges Franju"
          ],
          "dureeSeance": 120,
          "idCategorie": 4084,
          "idEvenement": 34845,
          "typeEvenement": 13,
          "idFilm": 34651,
          "titre": "Haute Pègre",
          "titreVo": "Trouble in Paradise",
          "realisateurs": "Ernst Lubitsch",
          "annee": 1932,
          "pays": "États-Unis",
          "duree": 83,
          "version": "VOSTF",
          "format": "DCP",
          "generique": [
            "Miriam Hopkins",
            "Kay Francis",
            "Herbert Marshall"
          ],
          "adaptation": "D'après la pièce _The Honest Finder_ de László Aladár.",
          "textes": [
            {
              "typeTexte": 1000,
              "texte": "Les aventures, à travers l'Europe, de deux escrocs indomptables, qui projettent de voler une riche et jolie veuve. À l'intrigue classique, Lubitsch ajoute sa botte secrète et signe une comédie de haut vol, à la fois sophistiquée et ciselée, qui mêle la perversité et la malice des jeux de désir, dans un sommet d'humour glamour, pré-code Hays."
            }
          ]
        },
        {
          "idSeance": 208652,
          "ordre": 1,
          "dateHeure": "2026-03-26T16:30:00",
          "idSalle": [
            "GF",
            "Georges Franju"
          ],
          "dureeSeance": 135,
          "idCategorie": 4084,
          "idEvenement": 34822,
          "typeEvenement": 13,
          "idFilm": 50877,
          "art": "La",
          "titre": "Règle du jeu",
          "realisateurs": "Jean Renoir",
          "annee": 1939,
          "pays": "France",
          "duree": 106,
          "version": "",
          "format": "DCP",
          "generique": [
            "Marcel Dalio",
            "Nora Gregor",
            "Roland Toutain",
            "Jean Renoir"
          ],
          "textes": [
            {
              "typeTexte": 1000,
              "texte": "_La_ référence cinématographique, le film de chevet des plus grands cinéastes... Avec une fluidité narrative incomparable, Renoir le Patron orchestre un chassé-croisé amoureux entre aristocrates et domestiques, lors d'une partie de chasse en Sologne. La fine fleur des vedettes de l'époque s'affronte dans une peinture de mœurs mordante, qui décortique avec génie la société française à la veille de la guerre. Chef-d'œuvre."
            }
          ]
        },
        {
          "idSeance": 208724,
          "ordre": 1,
          "dateHeure": "2026-03-23T16:00:00",
          "idSalle": [
            "GF",
            "Georges Franju"
          ],
          "dureeSeance": 120,
          "idCategorie": 4084,
          "idEvenement": 34836,
          "typeEvenement": 13,
          "idFilm": 48505,
          "art": "Les",
          "titre": "Yeux sans visage",
          "realisateurs": "Georges Franju",
          "annee": 1960,
          "pays": "France-Italie",
          "duree": 88,
          "version": "",
          "format": "DCP",
          "generique": [
            "Pierre Brasseur",
            "Edith Scob",
            "Alida Valli",
            "Juliette Mayniel",
            "François Guérin"
          ],
          "adaptation": "D'après le roman _Les Yeux sans visage_ de Jean Redon.",
          "textes": [
            {
              "typeTexte": 1000,
              "texte": "Avec Boileau et Narcejac, Franju a conçu un scénario diabolique : un chirurgien kidnappe des jeunes filles pour greffer leur peau sur le visage de sa fille, défigurée. Une 2CV, le ciré noir d'Alida Valli. Le regard pur d'Édith Scob derrière son masque inexpressif. Les noirs profonds et les blancs aveuglants signés Eugen Schüfftan, qui marquent chaque scène d'une beauté glaçante. Une référence de l'épouvante à la française, merveille poétique, qui inspirera des générations de cinéastes, de Jess Franco à John Carpenter ou Leos Carax."
            }
          ]
        }
      ],
      "textes": []
    }
  ],
  "textes": [],
  "info": {}
}