<?xml version="1.0" encoding="UTF-8"?><cycle title="Séances spéciales"><enTete><xTitreCycle>Séances spéciales&#xA;</xTitreCycle><action><actionSection title="Avant-premières"><xActionSectionTitre>Avant-premières&#xA;</xActionSectionTitre><xActionItem><xActionFilms>Le Cinquième plan de La Jetée&#xA;</xActionFilms></xActionItem><xActionDateHeure>►&#xA0;<xGrey>Lu 31 mar 20h00&#xA;</xGrey></xActionDateHeure><xActionItem><xActionFilms>Bulle Ogier, portrait d'une étoile cachée&#xA;</xActionFilms></xActionItem><xActionDateHeure>►&#xA0;<xGrey>Lu 21 avr 20h00&#xA;</xGrey></xActionDateHeure></actionSection><actionSection title="Conférence"><xActionSectionTitre>Conférence&#xA;</xActionSectionTitre><xActionItem><xActionTitre>Analyses d'analyses</xActionTitre>, par Nacim Belhadj et Vincent Deville&#xA;</xActionItem><xActionDateHeure>►&#xA0;<xGrey>Lu 28 avr 13h30&#xA;</xGrey></xActionDateHeure></actionSection></action></enTete><sousCycle title="Avant-première Dominique Cabrera"><xTitreSousCycle>Avant-première Dominique Cabrera&#xA;</xTitreSousCycle><xTexteSousCycle>Dominique Cabrera replace <xTexteSousCycle_Italic>La Jetée</xTexteSousCycle_Italic> de Chris Marker dans le contexte de l’année de sa création, 1962, marquée par l’indépendance algérienne et l’exode des pieds-noirs. Le cousin de la cinéaste, présent à Orly lors des prises de vue, pense se reconnaître dans le film. Cette découverte est le point de départ d’une enquête qui mêle histoire personnelle et réflexion cinématographique.&#xA;</xTexteSousCycle><film title="Le Cinquième plan de La Jetée"><xTitre_First>Le Cinquième plan de La Jetée&#xA;</xTitre_First><xRealisateurs>Dominique Cabrera&#xA;</xRealisateurs><xInfosTechniques>France. 2024. 97’. DCP&#xA;</xInfosTechniques><xInfosSeance>Lu 31 mar 20h00&#x202F;-&#x202F;HL&#xA;</xInfosSeance></film></sousCycle><sousCycle title="Prix Serge Daney"><xTitreSousCycle>Prix Serge Daney&#xA;</xTitreSousCycle><programme title="[Sans titre] (5 films)"><xTitre_First>Tapage&#xA;</xTitre_First><xRealisateurs>Joséphine Madinier&#xA;</xRealisateurs><xInfosTechniques>France. 2024. 29’. DCP&#xA;</xInfosTechniques><xTitre_VSpaceMin>Chers parents&#xA;</xTitre_VSpaceMin><xRealisateurs>Adèle Shaykhulova&#xA;</xRealisateurs><xInfosTechniques>France. 2024. 20’. DCP&#xA;</xInfosTechniques><xGenerique>Avec Jiangchaoping&#xA0;Li, Rémi&#xA0;Langlade, Franck&#xA0;Williams, Matthieu&#xA0;Lucci.&#xA;</xGenerique><xTitre_VSpaceMin>Emma&#xA;</xTitre_VSpaceMin><xRealisateurs>Éloïse Guimard&#xA;</xRealisateurs><xInfosTechniques>France. 2024. 15’. DCP&#xA;</xInfosTechniques><xGenerique>Avec Guilhaine&#xA0;Chambon, Patricia&#xA0;Samuel.&#xA;</xGenerique><xTitre_VSpaceMin>Orbes&#xA;</xTitre_VSpaceMin><xRealisateurs>Aurore Portales&#xA;</xRealisateurs><xInfosTechniques>France. 2024. 30’. DCP&#xA;</xInfosTechniques><xTitre_VSpaceMin>Lakeview Side&#xA;</xTitre_VSpaceMin><xRealisateurs>Wangsiwen Zhang&#xA;</xRealisateurs><xInfosTechniques>France. 2024. 14’. DCP&#xA;</xInfosTechniques><xInfosSeance_VSpace>Je 10 avr 18h00&#x202F;-&#x202F;JE&#xA;</xInfosSeance_VSpace></programme></sousCycle><sousCycle title="Avant-première Bulle Ogier par Eugénie Grandval"><xTitreSousCycle>Avant-première Bulle Ogier par Eugénie Grandval&#xA;</xTitreSousCycle><xTexteSousCycle>Eugénie Grandval convie différentes personnalités du cinéma pour évoquer l’œuvre et la personnalité de Bulle Ogier. Enrichi de nombreux extraits de films et d’entretiens puisés dans les archives de l’INA, le portrait intime d’une figure majeure du cinéma français.&#xA;</xTexteSousCycle><film title="Bulle Ogier, portrait d'une étoile cachée"><xTitre_First>Bulle Ogier, portrait d’une étoile cachée&#xA;</xTitre_First><xRealisateurs>Eugénie Grandval&#xA;</xRealisateurs><xInfosTechniques>France. 2024. 70’. DCP&#xA;</xInfosTechniques><xInfosSeance>Lu 21 avr 20h00&#x202F;-&#x202F;HL&#xA;</xInfosSeance></film></sousCycle><sousCycle title="Séance du programme de recherche Collimateur"><xTitreSousCycle>Séance du programme de recherche Collimateur&#xA;</xTitreSousCycle><xTexteSousCycle>Le programme de recherche Collimateur est centré sur l’histoire de l’analyse esthétique des films à partir de textes parus entre 1970 et 2020. Cette double conférence suivie d’une projection s’interroge ainsi sur les gestes d’analyse singuliers que ces écrits mettent en œuvre.&#xA;</xTexteSousCycle><groupe><conf title="Analyses d'analyses"><xTitreConf>Analyses d’analyses&#xA;</xTitreConf><xSousTitreConf>Conférence de Nacim Belhadj et Vincent Deville&#xA;</xSousTitreConf><xMiniTexte>À partir de deux textes, «&#xA0;Le travail du film, 2&#xA0;»&#xA0;(1975) et «&#xA0;L’écriture figurale dans le cinéma muet des années 20&#xA0;»&#xA0;(1999), qui emploient tous deux le concept de figural pour analyser <xMiniTexte_Italic>Les Chasses du comte Zaroff</xMiniTexte_Italic>&#xA0;(1932) et <xMiniTexte_Italic>Le Cabinet du docteur Caligari</xMiniTexte_Italic>&#xA0;(1920), Nacim Belhadj mettra en lumière les différences entre ces deux types d’usage du concept et dégagera leurs multiples enjeux théoriques.
Quand, dans un article paru dans les <xMiniTexte_Italic>Cahiers du cinéma</xMiniTexte_Italic>&#xA0;(2017), Nicole Brenez nous amène à voir dans <xMiniTexte_Italic>Les Derniers Parisiens</xMiniTexte_Italic> de Hamé et Ékoué un récit modeste mais doté de l’ambition de «&#xA0;rendre compte d’une génération oubliée dans un repli de l’histoire néocoloniale&#xA0;», elle y parvient par les moyens de l’analyse figurative. Une méthode par laquelle elle hisse au même niveau d’exigence l’attention portée aux films et la considération pour les figures de la précarité historique, ce dont il sera question dans la conférence de Vincent Deville.&#xA;</xMiniTexte><xInfosSeance>Lu 28 avr 13h30&#x202F;-&#x202F;JE&#xA;</xInfosSeance></conf><film title="Les Derniers Parisiens"><xTitre_VSpaceMin>Les Derniers Parisiens&#xA;</xTitre_VSpaceMin><xRealisateurs>Hamé et Ekoué&#xA;</xRealisateurs><xInfosTechniques>France. 2015. 105’. DCP&#xA;</xInfosTechniques><xGenerique>Avec Reda&#xA0;Kateb, Slimane&#xA0;Dazi, Mélanie&#xA0;Laurent.&#xA;</xGenerique><xInfosSeance>Lu 28 avr 16h30&#x202F;-&#x202F;JE&#xA0;<xMentionGroupe>Film choisi par le conférencier&#xA;</xMentionGroupe></xInfosSeance></film></groupe></sousCycle></cycle>