[
  {
    "idFilm": 30923,
    "titre": "Invasion Los Angeles",
    "titreVo": "They Live",
    "realisateurs": "John Carpenter",
    "annee": 1988,
    "pays": "États-Unis",
    "generique": [
      "Roddy Piper",
      "Keith David",
      "Meg Foster"
    ],
    "adaptation": "D'après la nouvelle _Eight O'Clock in the Morning_ de Ray Nelson.",
    "textes": [
      {
        "typeTexte": 9,
        "texte": "John Nada, ouvrier au chômage à Los Angeles, découvre des lunettes de soleil qui permettent de voir la société telle qu'elle est réellement : gouvernée par des extraterrestres à l'apparence humaine, qui maintiennent la population dans un état d'obéissance au moyen d'une propagande aussi subliminale qu'omniprésente."
      }
    ]
  },
  {
    "idFilm": 48044,
    "titre": "Parapluies de Cherbourg",
    "art": "Les",
    "realisateurs": "Jacques Demy",
    "annee": 1963,
    "pays": "France-RFA",
    "generique": [
      "Catherine Deneuve",
      "Nino Castelnuovo",
      "Anne Vernon"
    ],
    "textes": [
      {
        "typeTexte": 9,
        "texte": "Un jeune couple amoureux est séparé par la Guerre d'Algérie. Pour éviter la faillite et le déshonneur à sa mère endettée, la jeune fille, enceinte, se résigne à épouser un riche diamantaire."
      },
      {
        "typeTexte": 99,
        "texte": "Film restauré par Ciné Tamaris avec le soutien du Festival de Cannes, du CNC, de la Ville de Cherbourg et de la Région Basse-Normandie."
      }
    ]
  },
  {
    "idFilm": 44666,
    "titre": "Salamandre",
    "art": "La",
    "realisateurs": "Alain Tanner",
    "annee": 1970,
    "pays": "Suisse",
    "generique": [
      "Bulle Ogier",
      "Jean-Luc Bideau",
      "Jacques Denis"
    ],
    "textes": [
      {
        "typeTexte": 9,
        "texte": "Pierre et Paul, respectivement journaliste et écrivain, s'associent pour écrire un scénario d'après un fait divers : l'histoire d'une jeune fille accusée par son oncle d'avoir tenté de le tuer. Pour en savoir plus, ils tentent de la retrouver."
      }
    ]
  },
  {
    "idFilm": 137087,
    "titre": "Va, Toto !",
    "realisateurs": "Pierre Creton",
    "annee": 2016,
    "pays": "France",
    "generique": [
      "Ghislaine Paul-Cavallier",
      "Vincent Barré"
    ],
    "textes": [
      {
        "typeTexte": 9,
        "texte": "L'arrivée de Toto le marcassin chez Madeleine, le voyage de Vincent en Inde et ses démêlés avec les singes, ou les rêves de Joseph provoqués par une machine à pression continue. Trois histoires qui évoquent notre rapport à l'animal, cet autre prochain."
      },
      {
        "typeTexte": 99,
        "texte": "Prix du film singulier 2017 du Syndicat français de la critique de cinéma."
      }
    ]
  }
]