{
  "textePresentation": "",
  "sousCycles": [
    {
      "tri": 4,
      "titreSousCycle": "Les films",
      "items": [
        {
          "idFilm": 47977,
          "content": [
            {
              "idFilm": 47977,
              "ordre": 1,
              "titre": "Adieu blaireau",
              "realisateurs": "Bob Decout",
              "pays": "France",
              "annee": 1984,
              "duree": 88,
              "version": "",
              "format": "35 mm"
            }
          ],
          "seances": [
            {
              "idSeance": 188571,
              "dateHeure": "2025-05-30T19:00:00",
              "idSalle": "GF"
            }
          ]
        },
        {
          "idFilm": 51666,
          "content": [
            {
              "idFilm": 51666,
              "ordre": 1,
              "titre": "Un assassin qui passe",
              "realisateurs": "Michel Vianey",
              "pays": "France",
              "annee": 1980,
              "duree": 105,
              "version": "",
              "format": "35 mm"
            }
          ],
          "seances": [
            {
              "idSeance": 188572,
              "dateHeure": "2025-05-30T21:00:00",
              "idSalle": "GF"
            }
          ]
        },
        {
          "idFilm": 42416,
          "content": [
            {
              "idFilm": 42416,
              "ordre": 1,
              "titre": "Mystère",
              "realisateurs": "Carlo Vanzina",
              "pays": "Italie",
              "annee": 1983,
              "duree": 88,
              "version": "VF",
              "format": "35 mm",
              "generique": [
                "Carole Bouquet",
                "Phil Coccioletti",
                "Duilio Del Prete"
              ]
            }
          ],
          "seances": [
            {
              "idSeance": 188949,
              "dateHeure": "2025-06-13T19:30:00",
              "idSalle": "GF"
            }
          ]
        },
        {
          "idFilm": 44242,
          "content": [
            {
              "idFilm": 44242,
              "ordre": 1,
              "titre": "Baiser macabre",
              "titreVo": "Macabro",
              "realisateurs": "Lamberto Bava",
              "pays": "Italie",
              "annee": 1980,
              "duree": 89,
              "version": "VF",
              "format": "35 mm",
              "generique": [
                "Bernice Stegers",
                "Stanko Molnar",
                "Veronica Zinny"
              ]
            }
          ],
          "seances": [
            {
              "idSeance": 188950,
              "dateHeure": "2025-06-13T21:30:00",
              "idSalle": "GF"
            }
          ]
        },
        {
          "idFilm": 30274,
          "content": [
            {
              "idFilm": 30274,
              "ordre": 1,
              "titre": "Future Cop",
              "titreVo": "Trancers",
              "realisateurs": "Charles Band",
              "pays": "États-Unis",
              "annee": 1984,
              "duree": 77,
              "version": "VOSTF",
              "format": "35 mm",
              "generique": [
                "Tim Thomerson",
                "Helen Hunt",
                "Telma Hopkins"
              ],
              "isFocus": true,
              "miniTexte": "Double dose d'apocalypse chez le prolifique Charles Band, où se rencontrent flics, criminels et créatures bizarres. L'univers punk _eighties_ est porté à son paroxysme dans _Future Cop_, pêle-mêle de _gunfights_ et de poursuites au cœur d'un Los Angeles dévasté, qui lorgne copieusement sur _Blade Runner_. L'occasion pour Helen Hunt de décrocher son premier grand rôle à l'écran. Explosions de voitures et motos volantes prennent la suite dans _Metalstorm_, mélange hybride entre _Mad Max_ et _Les Aventuriers de l'arche perdue_, qui laisse à Jeffrey Byron un boulevard de cabotinage à sillonner."
            }
          ],
          "seances": [
            {
              "idSeance": 194576,
              "dateHeure": "2025-06-20T19:00:00",
              "idSalle": "GF"
            }
          ]
        },
        {
          "idFilm": 33015,
          "content": [
            {
              "idFilm": 33015,
              "ordre": 1,
              "titre": "Passagers de l'angoisse",
              "art": "Les",
              "titreVo": "Stranded",
              "realisateurs": "Tex Fuller",
              "pays": "États-Unis",
              "annee": 1987,
              "duree": 80,
              "version": "VF",
              "format": "35 mm",
              "generique": [
                "Ione Skye",
                "Maureen O'Sullivan",
                "Joe Morton"
              ]
            }
          ],
          "seances": [
            {
              "idSeance": 194577,
              "dateHeure": "2025-06-20T21:00:00",
              "idSalle": "GF"
            }
          ]
        }
      ]
    }
  ],
  "syntheseAction": {}
}