{
  "data": [
    {
      "titreSousCycle": "Rencontres et conférences",
      "tri": 4,
      "items": [
        {
          "idSeance": 115518,
          "dateHeure": "2023-12-01T17:30:00",
          "idSalle": [
            "GF",
            "Georges Franju"
          ],
          "dureeSeance": 90,
          "idCategorie": 1856,
          "idEvenement": 29511,
          "typeEvenement": 14,
          "idTypeConference": 55,
          "typeConference": "Conférence",
          "titre": "Conservatoire : 100 ans Warner – Stage 5, département d'effets spéciaux",
          "sousTitre": "Conférence de Réjane Hamus-Vallée et Claire Demoulin",
          "duree": 90,
          "textes": [],
          "intervenants": [
            {
              "nomComplet": "Réjane Hamus-Vallée",
              "idFonction": 139,
              "fonction": "Conférencier",
              "ordre": 1
            },
            {
              "nomComplet": "Claire Demoulin",
              "idFonction": 139,
              "fonction": "Conférencier",
              "ordre": 2
            }
          ]
        },
        {
          "idSeance": 115521,
          "dateHeure": "2024-02-02T17:00:00",
          "idSalle": [
            "GF",
            "Georges Franju"
          ],
          "dureeSeance": 120,
          "idCategorie": 1856,
          "idEvenement": 29513,
          "typeEvenement": 14,
          "idTypeConference": 55,
          "typeConference": "Conférence",
          "titre": "Conservatoire : Dans les airs – le cinéma aérien",
          "sousTitre": "Conférence ",
          "duree": 90,
          "textes": []
        },
        {
          "idSeance": 115520,
          "dateHeure": "2024-01-12T17:00:00",
          "idSalle": [
            "GF",
            "Georges Franju"
          ],
          "dureeSeance": 120,
          "idCategorie": 1856,
          "idEvenement": 29512,
          "typeEvenement": 14,
          "idTypeConference": 55,
          "typeConference": "Conférence",
          "titre": "Conservatoire : le montage",
          "sousTitre": "Conférence ",
          "duree": 90,
          "textes": []
        }
      ],
      "textes": []
    }
  ],
  "textes": [
    {
      "typeTexte": 8,
      "texte": "Le Conservatoire des techniques cinématographiques a été créé en 2008 par la Cinémathèque française. Il a pour mission d'étudier, inventorier, restaurer, valoriser cette collection, d'aider à l'écriture de l'histoire technique du cinéma et de continuer la collecte d'appareils anciens et récents. Dans cette optique, le Conservatoire des techniques organise, un vendredi par mois, à la Cinémathèque française, une conférence confiée à un spécialiste sur un point d'histoire précis. En partenariat avec les universités Paris I, Paris III, Paris VII et Paris X, la Commission supérieure technique, La fémis, l'École nationale supérieure Louis-Lumière et Ina Sup."
    }
  ],
  "info": {}
}