{
  "textePresentation": "",
  "sousCycles": [
    {
      "tri": 4,
      "titreSousCycle": "10 ans de la NEF",
      "items": [
        {
          "idEvenement": 36271,
          "content": [
            {
              "idFilm": 141119,
              "ordre": 1,
              "titre": "Vaysha l'aveugle",
              "titreVo": "Blind Vaysha",
              "realisateurs": "Theodore Ushev",
              "pays": "Canada-Bulgarie",
              "annee": 2016,
              "duree": 8,
              "version": "",
              "format": "DCP"
            },
            {
              "idFilm": 150602,
              "ordre": 2,
              "titre": "Rivages",
              "realisateurs": "Sophie Racine",
              "pays": "France",
              "annee": 2020,
              "duree": 8,
              "version": "",
              "format": "DCP"
            },
            {
              "idFilm": 155748,
              "ordre": 3,
              "titre": "Nun or Never",
              "realisateurs": "Heta Jäälinoja",
              "pays": "Finlande",
              "annee": 2023,
              "duree": 11,
              "version": "VOSTF",
              "format": "DCP"
            },
            {
              "idFilm": 155749,
              "ordre": 4,
              "titre": "Family Portrait",
              "realisateurs": " Lea Vidaković",
              "pays": "Serbie-Croatie",
              "annee": 2023,
              "duree": 15,
              "version": "VOSTF",
              "format": "DCP"
            },
            {
              "idFilm": 155750,
              "ordre": 5,
              "titre": "Hurikán",
              "realisateurs": "Jan Saska",
              "pays": "République tchèque",
              "annee": 2024,
              "duree": 13,
              "version": "VOSTF",
              "format": "DCP"
            },
            {
              "idFilm": 155751,
              "ordre": 6,
              "titre": "Quelque chose de divin",
              "realisateurs": "Bogdan Stamatin, Mélody Boulissière",
              "pays": "France-Roumanie",
              "annee": 2024,
              "duree": 14,
              "version": "VOSTF",
              "format": "DCP"
            },
            {
              "idFilm": 155752,
              "ordre": 7,
              "titre": "Je mordrai la poussière des étoiles",
              "realisateurs": "Kiana Naghshineh",
              "pays": "Allemagne-France",
              "annee": 2025,
              "duree": 14,
              "version": "",
              "format": "DCP"
            }
          ],
          "seances": [
            {
              "idSeance": 209291,
              "dateHeure": "2026-06-08T19:00:00",
              "idSalle": "JE",
              "mention": "Séance présentée par Xavier Kawa-Topor"
            }
          ]
        }
      ]
    }
  ],
  "syntheseAction": {
    "Séance présentée": [
      {
        "titreFilms": "Vaysha l'aveugle / Rivages / Nun or Never / Family Portrait / Hurikán / Quelque chose de divin / Je mordrai la poussière des étoiles",
        "mention": "par Xavier Kawa-Topor",
        "dateHeure": "2026-06-08T19:00:00"
      }
    ]
  }
}