{
  "data": [
    {
      "titreSousCycle": "Les films",
      "tri": 1,
      "items": [
        {
          "idSeance": 92487,
          "ordre": 1,
          "dateHeure": "2023-03-11T19:00:00",
          "idSalle": [
            "HL",
            "Henri Langlois"
          ],
          "dureeSeance": 135,
          "idCategorie": 2946,
          "idEvenement": 27539,
          "typeEvenement": 13,
          "idFilm": 102664,
          "art": "Le",
          "titre": "Gardien de l'enfer",
          "titreVo": "Jigoku no keibîn",
          "realisateurs": "Kiyoshi Kurosawa",
          "annee": 1992,
          "pays": "Japon",
          "duree": 97,
          "version": "VOSTF",
          "format": "DCP",
          "generique": [
            "Makiko Kuno",
            "Yutaka Matsushige",
            "Hatsunori Hasegawa"
          ],
          "textes": [
            {
              "typeTexte": 9,
              "texte": "Un ancien lutteur de sumo, devenu veilleur de nuit, est pris de pulsions meurtrières et enchaîne les crimes violents sans réelle motivation. Mais, un soir, une jeune femme est témoin du meurtre d'un de ses collègues."
            }
          ]
        }
      ],
      "textes": []
    },
    {
      "titreSousCycle": "Carte blanche à Kiyoshi Kurosawa",
      "tri": 1,
      "items": [
        {
          "idSeance": 100634,
          "ordre": 1,
          "dateHeure": "2023-03-08T12:00:00",
          "idSalle": [
            "HO",
            "Hors les murs"
          ],
          "dureeSeance": 150,
          "idCategorie": 2952,
          "idEvenement": 27542,
          "typeEvenement": 13,
          "idFilm": 133144,
          "titre": "Alliés",
          "titreVo": "Allied",
          "realisateurs": "Robert Zemeckis",
          "annee": 2016,
          "pays": "États-Unis",
          "duree": 121,
          "version": "VOSTF",
          "format": "DCP",
          "generique": [
            "Brad Pitt",
            "Marion Cotillard",
            "Jared Harris"
          ],
          "textes": [
            {
              "typeTexte": 9,
              "texte": "Casablanca, 1942. Max et Marianne, deux espions des forces alliées, tombent amoureux lors d'une mission et se marient. Mais Max est informé par les services secrets britanniques que Marianne pourrait être une espionne allemande."
            }
          ]
        },
        {
          "idSeance": 92490,
          "ordre": 1,
          "dateHeure": "2023-03-11T16:30:00",
          "idSalle": [
            "GF",
            "Georges Franju"
          ],
          "dureeSeance": 105,
          "mention": "Séance présentée par Kiyoshi Kurosawa",
          "idCategorie": 2952,
          "idEvenement": 27540,
          "typeEvenement": 13,
          "idFilm": 77471,
          "titre": "Armored Car Robbery",
          "realisateurs": "Richard Fleischer",
          "annee": 1950,
          "pays": "États-Unis",
          "duree": 67,
          "version": "VOSTF",
          "format": "35 mm",
          "generique": [
            "Charles McGraw",
            "Adele Jergens",
            "William Talman"
          ],
          "textes": [
            {
              "typeTexte": 9,
              "texte": "Dave Purvis, dangereux criminel, reste inconnu de la police. Il organise minutieusement le braquage d'un fourgon blindé pendant un match de baseball. Mais les choses tournent mal, et l'inspecteur Cordell se lance à la poursuite de sa bande."
            }
          ]
        },
        {
          "idSeance": 100620,
          "ordre": 1,
          "dateHeure": "2023-03-12T18:45:00",
          "idSalle": [
            "JE",
            "Jean Epstein"
          ],
          "dureeSeance": 105,
          "idCategorie": 2952,
          "idEvenement": 27540,
          "typeEvenement": 13,
          "idFilm": 77471,
          "titre": "Armored Car Robbery",
          "realisateurs": "Richard Fleischer",
          "annee": 1950,
          "pays": "États-Unis",
          "duree": 67,
          "version": "VOSTF",
          "format": "35 mm",
          "generique": [
            "Charles McGraw",
            "Adele Jergens",
            "William Talman"
          ],
          "textes": [
            {
              "typeTexte": 9,
              "texte": "Dave Purvis, dangereux criminel, reste inconnu de la police. Il organise minutieusement le braquage d'un fourgon blindé pendant un match de baseball. Mais les choses tournent mal, et l'inspecteur Cordell se lance à la poursuite de sa bande."
            }
          ]
        }
      ],
      "textes": []
    },
    {
      "titreSousCycle": "Rencontres et conférences",
      "tri": 4,
      "items": [
        {
          "idSeance": 100571,
          "dateHeure": "2023-03-11T20:15:00",
          "idSalle": [
            "HL",
            "Henri Langlois"
          ],
          "dureeSeance": 75,
          "idCategorie": 2986,
          "idEvenement": 27897,
          "typeEvenement": 14,
          "idTypeConference": 145,
          "typeConference": "MasterClass",
          "titre": "Masterclass Kiyoshi Kurosawa",
          "duree": 90,
          "textes": [],
          "intervenants": [
            {
              "nomComplet": "Kiyoshi Kurosawa",
              "idFonction": 142,
              "fonction": "Interviewé",
              "ordre": 1
            },
            {
              "nomComplet": "Jean-François Rauger",
              "idFonction": 40,
              "fonction": "Animateur",
              "ordre": 2
            }
          ],
          "mentionAnimation": "Rencontre animée par Jean-François Rauger"
        }
      ],
      "textes": []
    }
  ],
  "textes": [
    {
      "typeTexte": 263,
      "texte": "Park Circus, The Jokers Films, Toei Company, Mme Nanako Tsukidate, M. Daichi Yashiki."
    }
  ],
  "info": {}
}