[
  {
    "idFilm": 154424,
    "titre": "27",
    "realisateurs": "Flóra Anna Buda",
    "annee": 2023,
    "pays": "France-Hongrie",
    "textes": [
      {
        "typeTexte": 9,
        "texte": "Alice a 27 ans et vit chez ses parents. Elle n'a ni vie privée, ni relation amoureuse. De retour à vélo de sa soirée d'anniversaire, elle a un accident. En sortant du coma, elle réalise qu'il est temps pour elle de partir."
      }
    ]
  },
  {
    "idFilm": 154404,
    "titre": "Christopher At Sea",
    "realisateurs": "Tom CJ Brown",
    "annee": 2022,
    "pays": "France-Grande-Bretagne-États-Unis",
    "textes": [
      {
        "typeTexte": 9,
        "texte": "Christopher s'embarque pour un voyage transatlantique en tant que passager d'un cargo. Son espoir de découvrir ce qui attire tant d'hommes en mer l'entraîne dans un voyage vers la solitude, le fantasme et l'obsession."
      }
    ]
  },
  {
    "idFilm": 154423,
    "titre": "Cicada",
    "realisateurs": "Daewoen Yoon",
    "annee": 2021,
    "pays": "Corée",
    "generique": [
      "Nina Kim",
      "Ejae Jung"
    ],
    "textes": [
      {
        "typeTexte": 9,
        "texte": "Changhyeon, une prostituée transgenre, rencontre un client qui lui semble à la fois familier et inconnu."
      }
    ]
  },
  {
    "idFilm": 154403,
    "titre": "Coupeur de route",
    "realisateurs": "Christophe Granger",
    "annee": 2022,
    "pays": "France",
    "generique": [
      "Théo Augier Bonaventure",
      "Aurélie Lannoy"
    ],
    "textes": [
      {
        "typeTexte": 9,
        "texte": "Nino, dix-neuf ans, est un vagabond des autoroutes. Il n'attend que l'été et le soleil pour pouvoir partir, faire la route, dormir dehors. Un jour, au détour d'une aire de repos, il rencontre Sarah."
      }
    ]
  },
  {
    "idFilm": 154406,
    "titre": "Dents du bonheur",
    "art": "Les",
    "realisateurs": "Joséphine Darcy Hopkins",
    "annee": 2022,
    "pays": "France",
    "generique": [
      "Lou Deleuze",
      "Katell Vavat",
      "Pauline Lorillard"
    ],
    "textes": [
      {
        "typeTexte": 9,
        "texte": "Madeleine, huit ans, accompagne sa mère esthéticienne à domicile chez de nouvelles clientes. Arrivée à la maison, elle fait la connaissance d'Eugénie, Constance et Émeraude, qui l'invitent au sous-sol à participer à un cruel jeu de société."
      }
    ]
  },
  {
    "idFilm": 154325,
    "titre": "Fifi",
    "realisateurs": "Paul Saintillan, Jeanne Aslan",
    "annee": 2021,
    "pays": "France",
    "generique": [
      "Céleste Brunnquell",
      "Quentin Dolmaire",
      "Chloé Mons",
      "Meghan Northam"
    ],
    "textes": [
      {
        "typeTexte": 9,
        "texte": "À 15 ans, Sophie, alias Fifi, voudrait bien profiter de l'été. Quand elle croise une ancienne amie sur le point de partir en voyage, elle lui dérobe les clés de sa maison, désertée pour les vacances. Elle s'y installe en cachette."
      }
    ]
  },
  {
    "idFilm": 154402,
    "titre": "Forêt Debussy",
    "realisateurs": "Cheng-Chui Kuo",
    "annee": 2016,
    "pays": "Taïwan",
    "generique": [
      "Gwei Lun-Mei",
      "Lu Yi-ching"
    ],
    "textes": [
      {
        "typeTexte": 9,
        "texte": "Le voyage d'une fille et de sa mère dans une forêt dense où personne ne pourra jamais les retrouver."
      }
    ]
  },
  {
    "idFilm": 154421,
    "titre": "Georgia",
    "realisateurs": "Jayil Pak",
    "annee": 2020,
    "pays": "Corée",
    "generique": [
      "Yanghee Lee",
      "Chaekyung Lee",
      "Seonwoo Hong"
    ],
    "textes": [
      {
        "typeTexte": 9,
        "texte": "Lorsque la police refuse d'enquêter sur le suicide présumé de leur fille, deux parents décident de concevoir une banderole de protestation."
      }
    ]
  },
  {
    "idFilm": 154405,
    "titre": "Jeanne Dinde",
    "realisateurs": "Pauline Ouvrard",
    "annee": 2022,
    "pays": "France",
    "textes": [
      {
        "typeTexte": 9,
        "texte": "Jeanne, 13 ans a pour seule amie la dinde qui vit dans son jardin qui l'incite à ne pas grandir pour ne pas se trahir.... Mais Jeanne a des désirs de changements ..."
      }
    ]
  },
  {
    "idFilm": 154407,
    "titre": "La Sorcière et le martien",
    "realisateurs": "Thomas Bardinet",
    "annee": 2023,
    "pays": "France",
    "generique": [
      "Yasmine Kherbouche",
      "Kylian Mahamoud",
      "Théodore Dupleix"
    ],
    "textes": [
      {
        "typeTexte": 9,
        "texte": "Myriam, orpheline, apprend qu'elle va changer de famille d'accueil. Souvent moquée pour sa naïveté, elle voit des animaux qui parlent ou des sorcières bienveillantes. Elle seule pourrait croire au destin du jeune Bilal qui va rejoindre ses parents scientifiques sur la planète Mars. Ce premier jour d'été sera pour les tous deux le dernier qu'ils vivront sur le territoire de leur enfance."
      }
    ]
  },
  {
    "idFilm": 154425,
    "titre": "Ligne",
    "art": "La",
    "realisateurs": "Ursula Meier",
    "annee": 2022,
    "pays": "Suisse-France-Belgique",
    "generique": [
      "Stéphanie Blanchoud",
      "Elli Spagnolo"
    ],
    "textes": [
      {
        "typeTexte": 9,
        "texte": "Après avoir agressé violemment sa mère, Margaret, 35 ans, doit se soumettre à une mesure stricte d'éloignement en attendant son jugement. Mais cette distance qui la sépare de son foyer ne fait qu'exacerber son désir de se rapprocher des siens."
      }
    ]
  },
  {
    "idFilm": 154422,
    "titre": "Nowhere Else",
    "realisateurs": "Kyeongwon Lee",
    "annee": 2021,
    "pays": "Corée",
    "generique": [
      "Jaechul Kim",
      "Jihye Jung",
      "Euijin Jo"
    ],
    "textes": [
      {
        "typeTexte": 9,
        "texte": "Une femme disparue depuis 6 ans réapparaît dans sa ville d'origine avec un nouveau mari."
      }
    ]
  }
]