<?xml version="1.0" encoding="UTF-8"?><cycle title="Boris Barnet"><enTete><xTitreCycle>Boris Barnet&#xA;</xTitreCycle><xDatesCycle>14 février - 10 mars 2024&#xA;</xDatesCycle></enTete><sousCycle title="Les films"><film title="Alenka"><xTitre_First>Alenka&#xA;</xTitre_First><xRealisateurs>Boris Barnet&#xA;</xRealisateurs><xInfosTechniques>URSS. 1961. 88’. 35&#xA0;mm. VOSTA&#xA;</xInfosTechniques><xGenerique>Avec Natalya&#xA0;Ovodova, Irina&#xA0;Zarubina.&#xA;</xGenerique><xInfosSeance>Di 10 mar 20h15&#x202F;-&#x202F;GF&#xA;</xInfosSeance></film><film title="Annouchka"><xTitre>Annouchka&#xA;</xTitre><xRealisateurs>Boris Barnet&#xA;</xRealisateurs><xInfosTechniques>URSS. 1959. 88’. 35&#xA0;mm. VOSTF&#xA;</xInfosTechniques><xInfosSeance>Di 10 mar 18h00&#x202F;-&#x202F;GF&#xA;</xInfosSeance></film><film title="Au bord de la mer bleue"><xTitre>Au bord de la mer bleue&#xA;</xTitre><xTitreVo>(Ou samogo sinego moria)&#xA;</xTitreVo><xRealisateurs>Boris Barnet&#xA;</xRealisateurs><xInfosTechniques>URSS. 1935. 70’. 35&#xA0;mm. VOSTF&#xA;</xInfosTechniques><xGenerique>Avec Lev&#xA0;Sverdline, Nikolay&#xA0;Kryuchkov, Elena&#xA0;Kouzmina.&#xA;</xGenerique><xInfosSeance>Me 14 fév 20h00&#x202F;-&#x202F;HL&#xA0;<xMention>Ouverture de la rétrospective</xMention>&#xA;</xInfosSeance></film><film title="Concert des maîtres de l'art ukrainien"><xTitre>Concert des maîtres de l’art ukrainien&#xA;</xTitre><xTitreVo>(Kontsert masterov ukrainskogo iskousstva)&#xA;</xTitreVo><xRealisateurs>Boris Barnet&#xA;</xRealisateurs><xInfosTechniques>URSS. 1952. 78’. 16&#xA0;mm. VOSTF&#xA;</xInfosTechniques><xGenerique>Avec Gmirya, Lydia&#xA0;Gerasimchuk.&#xA;</xGenerique><xInfosSeance>Di 25 fév 18h00&#x202F;-&#x202F;JE&#xA;</xInfosSeance></film><film title="L'Exploit d'un éclaireur"><xTitre>L’Exploit d’un éclaireur&#xA;</xTitre><xTitreVo>(Podvig razvedtchika)&#xA;</xTitreVo><xRealisateurs>Boris Barnet&#xA;</xRealisateurs><xInfosTechniques>URSS. 1947. 120’. 35&#xA0;mm&#xA;</xInfosTechniques><xInfosSeance>Di 18 fév 17h30&#x202F;-&#x202F;JE&#xA;</xInfosSeance></film><film title="La Fonte des glaces"><xTitre>La Fonte des glaces&#xA;</xTitre><xTitreVo>(Ledolom)&#xA;</xTitreVo><xRealisateurs>Boris Barnet&#xA;</xRealisateurs><xInfosTechniques>URSS. 1931. 65’. 35&#xA0;mm&#xA;</xInfosTechniques><xInfosSeance>Me 06 mar 19h45&#x202F;-&#x202F;GF&#xA;</xInfosSeance></film><film title="La Jeune fille au carton à chapeau"><xTitre>La Jeune fille au carton à chapeau&#xA;</xTitre><xTitreVo>(Devouchka s korobkoï)&#xA;</xTitreVo><xRealisateurs>Boris Barnet&#xA;</xRealisateurs><xInfosTechniques>URSS. 1927. 60’. 35&#xA0;mm. VOSTF&#xA;</xInfosTechniques><xInfosSeance>Di 18 fév 15h00&#x202F;-&#x202F;HL&#xA;</xInfosSeance></film><film title="Le Lutteur et le clown"><xTitre>Le Lutteur et le clown&#xA;</xTitre><xTitreVo>(Borets i kloun)&#xA;</xTitreVo><xRealisateurs>Boris Barnet, Constantin Youdine&#xA;</xRealisateurs><xInfosTechniques>URSS. 1957. 95’. 35&#xA0;mm&#xA;</xInfosTechniques><xGenerique>Avec Stanislav&#xA0;Tchekan, Alexandre&#xA0;Mikhailov, Boris&#xA0;Petker.&#xA;</xGenerique><xInfosSeance>Sa 24 fév 21h00&#x202F;-&#x202F;GF&#xA;</xInfosSeance></film><groupe><film title="La Maison de la rue Troubnaïa"><xTitre>La Maison de la rue Troubnaïa&#xA;</xTitre><xTitreVo>(Dom na Trubnoï)&#xA;</xTitreVo><xRealisateurs>Boris Barnet&#xA;</xRealisateurs><xInfosTechniques>URSS. 1927. 65’. DCP. VO&#xA;</xInfosTechniques><xGenerique>Avec Vera&#xA0;Maretskaïa, Vladimir&#xA0;Fogel, Vladimir&#xA0;Batalov, Anna&#xA0;Soudakevitch.&#xA;</xGenerique></film><conf title="Film + Dialogue avec Bernard Eisenschitz"><xTitreConf_VSpaceMin>Film&#x202F;+&#x202F;Dialogue avec Bernard Eisenschitz&#xA;</xTitreConf_VSpaceMin><xMentionAnimation>Animé par Bernard Benoliel&#xA;</xMentionAnimation><xInfosSeance>Sa 17 fév 16h45&#x202F;-&#x202F;GF&#xA0;<xMentionGroupe>Film seul</xMentionGroupe>&#xA;</xInfosSeance><xInfosSeance>Sa 24 fév 14h30&#x202F;-&#x202F;GF&#xA0;<xMentionGroupe>Film&#x202F;+&#x202F;dialogue</xMentionGroupe>&#xA;</xInfosSeance></conf></groupe><film title="Miss Mend"><xTitre>Miss Mend&#xA;</xTitre><xRealisateurs>Fedor Ozep, Boris Barnet&#xA;</xRealisateurs><xInfosTechniques>URSS. 1926. 250’. 35&#xA0;mm. VO&#xA;</xInfosTechniques><xInfosSeance>Ve 16 fév 18h30&#x202F;-&#x202F;GF&#xA;</xInfosSeance></film><film title="Moscou en octobre"><xTitre>Moscou en octobre&#xA;</xTitre><xTitreVo>(Moskva v oktiabre)&#xA;</xTitreVo><xRealisateurs>Boris Barnet&#xA;</xRealisateurs><xInfosTechniques>URSS. 1929. 44’. 35&#xA0;mm. Autres&#xA;</xInfosTechniques><xInfosSeance>Me 06 mar 18h30&#x202F;-&#x202F;GF&#xA;</xInfosSeance></film><groupe><film title="Okraïna"><xTitre>Okraïna&#xA;</xTitre><xRealisateurs>Boris Barnet&#xA;</xRealisateurs><xInfosTechniques>URSS. 1933. 96’. 35&#xA0;mm. VOSTF&#xA;</xInfosTechniques><xGenerique>Avec Alexandre&#xA0;Tchistiakov, Nikolaï&#xA0;Bogolioubov, Nikolaï&#xA0;Krioutchkov, Elena&#xA0;Kouzmina.&#xA;</xGenerique></film><conf title="Film + Dialogue avec Bernard Eisenschitz"><xTitreConf_VSpaceMin>Film&#x202F;+&#x202F;Dialogue avec Bernard Eisenschitz&#xA;</xTitreConf_VSpaceMin><xMentionAnimation>Animé par Bernard Benoliel&#xA;</xMentionAnimation><xInfosSeance_VSpace>Sa 17 fév 14h30&#x202F;-&#x202F;GF&#xA;</xInfosSeance_VSpace></conf></groupe><film title="Les Pages de la vie"><xTitre>Les Pages de la vie&#xA;</xTitre><xTitreVo>(Stranitsy jizni)&#xA;</xTitreVo><xRealisateurs>Boris Barnet&#xA;</xRealisateurs><xInfosTechniques>URSS. 1948. 90’. 35&#xA0;mm&#xA;</xInfosTechniques><xInfosSeance>Di 18 fév 20h00&#x202F;-&#x202F;JE&#xA;</xInfosSeance></film><film title="La Petite gare"><xTitre>La Petite gare&#xA;</xTitre><xTitreVo>(Poloustanok)&#xA;</xTitreVo><xRealisateurs>Boris Barnet&#xA;</xRealisateurs><xInfosTechniques>URSS. 1963. 70’. 35&#xA0;mm&#xA;</xInfosTechniques><xInfosSeance>Je 22 fév 18h30&#x202F;-&#x202F;GF&#xA;</xInfosSeance></film><film title="Le Poète"><xTitre>Le Poète&#xA;</xTitre><xTitreVo>(Poet)&#xA;</xTitreVo><xRealisateurs>Boris Barnet&#xA;</xRealisateurs><xInfosTechniques>URSS. 1957. 35&#xA0;mm&#xA;</xInfosTechniques><xInfosSeance>Sa 09 mar 19h45&#x202F;-&#x202F;GF&#xA;</xInfosSeance></film><film title="Un brave garçon"><xTitre>Un brave garçon&#xA;</xTitre><xTitreVo>(Slavny maly)&#xA;</xTitreVo><xRealisateurs>Boris Barnet&#xA;</xRealisateurs><xInfosTechniques>URSS. 1942. 67’. 35&#xA0;mm&#xA;</xInfosTechniques><xInfosSeance>Sa 17 fév 19h00&#x202F;-&#x202F;JE&#xA;</xInfosSeance></film><film title="Un été prodigieux"><xTitre>Un été prodigieux&#xA;</xTitre><xTitreVo>(Chtchedroe leto)&#xA;</xTitreVo><xRealisateurs>Boris Barnet&#xA;</xRealisateurs><xInfosTechniques>URSS. 1951. 87’. 35&#xA0;mm. VOSTA&#xA;</xInfosTechniques><xInfosSeance>Di 25 fév 16h00&#x202F;-&#x202F;JE&#xA;</xInfosSeance></film><film title="Une fois, la nuit"><xTitre>Une fois, la nuit&#xA;</xTitre><xTitreVo>(Odnajdy notchiou)&#xA;</xTitreVo><xRealisateurs>Boris Barnet&#xA;</xRealisateurs><xInfosTechniques>URSS. 1944. 88’. 35&#xA0;mm. VOSTF&#xA;</xInfosTechniques><xGenerique>Avec Irina&#xA0;Radchenko, Boris&#xA0;Barnet, Boris&#xA0;Andréev.&#xA;</xGenerique><xInfosSeance>Je 22 fév 20h30&#x202F;-&#x202F;GF&#xA;</xInfosSeance></film><film title="Une nuit de septembre"><xTitre>Une nuit de septembre&#xA;</xTitre><xTitreVo>(Notch v sentiabre)&#xA;</xTitreVo><xRealisateurs>Boris Barnet&#xA;</xRealisateurs><xInfosTechniques>URSS. 1939. 35&#xA0;mm&#xA;</xInfosTechniques><xInfosSeance>Sa 09 mar 17h30&#x202F;-&#x202F;GF&#xA;</xInfosSeance></film><film title="Le Vieux cavalier"><xTitre>Le Vieux cavalier&#xA;</xTitre><xTitreVo>(Stary naïezdnik)&#xA;</xTitreVo><xRealisateurs>Boris Barnet&#xA;</xRealisateurs><xInfosTechniques>URSS. 1940. 96’&#xA;</xInfosTechniques><xInfosSeance>Sa 17 fév 16h45&#x202F;-&#x202F;JE&#xA;</xInfosSeance></film></sousCycle></cycle>