{
  "cycle": {
    "779": []
  },
  "cats": {
    "3366": [
      {
        "typeTexte": 8,
        "texte": "Événement à la Cinémathèque, avec la projection d'un des plus grands films de l'histoire du cinéma, magnifié par la nouvelle partition miraculeuse de Simon Cloquet-Lafollye. Constant objet de fascination, tourné par un visionnaire qui voulait réinventer le cinéma, _Napoléon vu par Abel Gance_ aura été une étoile filante avant de vivre près d'un siècle avec ses couches de légende. De cette épopée maudite à la durée hors normes, on aura tout dit. Le monument expérimental qui accumule les morceaux de bravoure. Le portrait d'un homme qui écrira le siècle, le souffle de l'Histoire, la puissance, l'inventivité folle. Les montages parallèles qui convoquent D. W. Griffith, les triptyques, les essais de superposition et d'échos. L'audace et la maîtrise, le génie et le culot de scènes impossibles devenues inoubliables. Une fresque entre le grandiose et l'intime, non dénuée d'humour, où l'on frissonne et où la gorge se serre. Un chef-d'œuvre ab-so-lu."
      }
    ]
  }
}
