[
  {
    "titre": "Brigitte et Brigitte bande-annonce",
    "titreVo": "",
    "idFilm": 150383,
    "ageMinimal": null,
    "realisateurs": "Luc Moullet",
    "annee": 1965,
    "pays": "France"
  },
  {
    "titre": "Comédie du travail bande-annonce",
    "art": "La",
    "titreVo": "",
    "idFilm": 150373,
    "ageMinimal": null,
    "realisateurs": "Luc Moullet",
    "annee": 1987,
    "pays": "France"
  },
  {
    "titre": "Empreinte du passé",
    "art": "L'",
    "titreVo": "Road to Yesterday",
    "artVo": "The",
    "idFilm": 31591,
    "ageMinimal": null,
    "realisateurs": "Cecil B. DeMille",
    "annee": 1925,
    "pays": "États-Unis",
    "textes": [
      {
        "typeTexte": 9,
        "texte": "À la suite d'un accident, quatre personnes se retrouvent au Moyen-âge, victimes d'une malédiction."
      }
    ],
    "generique": [
      "Joseph Schildkraut",
      "Jetta Goudal",
      "William Boyd"
    ]
  },
  {
    "titre": "Léa, Léa et Léa",
    "titreVo": "",
    "idFilm": 150353,
    "ageMinimal": null,
    "realisateurs": "Collectif Film",
    "annee": 2001,
    "pays": "France",
    "textes": [
      {
        "typeTexte": 9,
        "texte": "Film d'école, monitoré par Moullet, sequel de « Chaînes conjugales » de Mankiewicz avec référence à Adie Ross, l'héroïne qu'on ne voit jamais et à la danse de sept voiles de Salomé."
      }
    ]
  },
  {
    "titre": "Mademoiselle Else",
    "titreVo": "",
    "idFilm": 131927,
    "ageMinimal": null,
    "realisateurs": "Isabelle Prim",
    "annee": 2010,
    "pays": "France",
    "textes": [
      {
        "typeTexte": 9,
        "texte": "Les derniers jours d'une jeune fille de bonne famille qui, en vacances dans les Alpes, est contrainte de demander de l'argent à Dorsday, un vieux jouisseur, marchand d'art, pour sauver son père, un avocat viennois criblé de dettes."
      }
    ]
  },
  {
    "titre": "Naufragés de la D 17 bande-annonce",
    "art": "Les",
    "titreVo": "",
    "idFilm": 150375,
    "ageMinimal": null,
    "realisateurs": "Luc Moullet",
    "annee": 2001,
    "pays": "France"
  },
  {
    "titre": "Prélude à l'après-midi d'un vieux faune",
    "titreVo": "",
    "idFilm": 150355,
    "ageMinimal": null,
    "realisateurs": "Esther Archambault",
    "annee": 2021,
    "pays": "France",
    "textes": [
      {
        "typeTexte": 9,
        "texte": "Une danse de Moullet à la Cro-magnon sur messe Pour le temps présent."
      },
      {
        "typeTexte": 99,
        "texte": "Extrait de trois minutes."
      }
    ]
  },
  {
    "titre": "Système Moullet",
    "art": "Le",
    "titreVo": "",
    "idFilm": 150370,
    "ageMinimal": null,
    "realisateurs": "André S. Labarthe",
    "annee": 2009,
    "pays": "France",
    "textes": [
      {
        "typeTexte": 9,
        "texte": "À l'occasion d'une série d'entretiens avec Emmanuel Burdeau et Jean Narboni, Luc Moullet donne un aperçu concret de sa méthode de travail"
      }
    ]
  },
  {
    "titre": "Terre de la folie bande-annonce",
    "art": "La",
    "titreVo": "",
    "idFilm": 150372,
    "ageMinimal": null,
    "realisateurs": "Luc Moullet",
    "annee": 2008,
    "pays": "France"
  },
  {
    "titre": "Une aventure de Billy the Kid bande-annonce",
    "titreVo": "",
    "idFilm": 150374,
    "ageMinimal": null,
    "realisateurs": "Luc Moullet",
    "annee": 1970,
    "pays": "France"
  }
]