[
  {
    "idCategorie": 1856,
    "typeEvenement": 14,
    "idEvenement": 33142,
    "idSeance": 194807,
    "dateHeure": "2025-06-13T17:00:00",
    "idSalle": [
      "HL",
      "Henri Langlois"
    ],
    "dureeSeance": 150,
    "items": [
      {}
    ]
  },
  {
    "idCategorie": 3813,
    "typeEvenement": 13,
    "idEvenement": 33284,
    "idSeance": 194907,
    "dateHeure": "2025-06-13T20:30:00",
    "idSalle": [
      "HL",
      "Henri Langlois"
    ],
    "dureeSeance": 90,
    "items": [
      {
        "idFilm": 32008,
        "ordre": 1
      }
    ],
    "mention": "Séance présentée par Walter Murch"
  }
]