{
  "data": [
    {
      "titreSousCycle": "Les films",
      "tri": 1,
      "items": [
        {
          "idSeance": 131674,
          "ordre": 1,
          "dateHeure": "2024-09-22T17:30:00",
          "idSalle": [
            "GF",
            "Georges Franju"
          ],
          "dureeSeance": 135,
          "idCategorie": 3383,
          "idEvenement": 30905,
          "typeEvenement": 13,
          "idFilm": 122494,
          "titre": "Arrête ou je continue",
          "realisateurs": "Sophie Fillières",
          "annee": 2013,
          "pays": "France",
          "duree": 102,
          "version": "",
          "format": "DCP",
          "generique": [
            "Emmanuelle Devos",
            "Mathieu Amalric",
            "Anne Brochet"
          ],
          "textes": []
        },
        {
          "idSeance": 131536,
          "ordre": 1,
          "dateHeure": "2024-09-18T20:30:00",
          "idSalle": [
            "GF",
            "Georges Franju"
          ],
          "dureeSeance": 30,
          "idCategorie": 3383,
          "idEvenement": 30901,
          "typeEvenement": 13,
          "idFilm": 69656,
          "titre": "Aïe",
          "realisateurs": "Sophie Fillières",
          "annee": 1999,
          "pays": "France",
          "duree": 113,
          "version": "",
          "format": "35 mm",
          "generique": [
            "André Dussollier",
            "Hélène Fillières",
            "Emmanuelle Devos",
            "Gisèle Casadesus"
          ],
          "textes": []
        },
        {
          "idSeance": 131675,
          "ordre": 1,
          "dateHeure": "2024-09-22T20:00:00",
          "idSalle": [
            "GF",
            "Georges Franju"
          ],
          "dureeSeance": 30,
          "idCategorie": 3383,
          "idEvenement": 30904,
          "typeEvenement": 13,
          "idFilm": 138499,
          "art": "La",
          "titre": "Belle et la belle",
          "realisateurs": "Sophie Fillières",
          "annee": 2017,
          "pays": "France",
          "duree": 95,
          "version": "",
          "format": "",
          "generique": [
            "Sandrine Kiberlain",
            "Agathe Bonitzer",
            "Melvil Poupaud"
          ],
          "textes": []
        },
        {
          "idSeance": 131655,
          "ordre": 1,
          "dateHeure": "2024-09-21T15:00:00",
          "idSalle": [
            "GF",
            "Georges Franju"
          ],
          "dureeSeance": 30,
          "idCategorie": 3383,
          "idEvenement": 30903,
          "typeEvenement": 13,
          "idFilm": 97823,
          "titre": "Gentille",
          "realisateurs": "Sophie Fillières",
          "annee": 2004,
          "pays": "France",
          "duree": 102,
          "version": "",
          "format": "35 mm",
          "generique": [
            "Emmanuelle Devos",
            "Lambert Wilson",
            "Bruno Todeschini",
            "Michael Lonsdale",
            "Bulle Ogier"
          ],
          "textes": []
        },
        {
          "idSeance": 131535,
          "ordre": 1,
          "dateHeure": "2024-09-18T18:30:00",
          "idSalle": [
            "GF",
            "Georges Franju"
          ],
          "dureeSeance": 30,
          "idCategorie": 3383,
          "idEvenement": 30906,
          "typeEvenement": 13,
          "idFilm": 52078,
          "titre": "Grande petite",
          "realisateurs": "Sophie Fillières",
          "annee": 1993,
          "pays": "France",
          "duree": 105,
          "version": "",
          "format": "35 mm",
          "generique": [
            "Judith Godrèche",
            "Hélène Fillières",
            "Emmanuel Salinger"
          ],
          "textes": []
        },
        {
          "idSeance": 131495,
          "ordre": 1,
          "dateHeure": "2024-09-16T20:00:00",
          "idSalle": [
            "HL",
            "Henri Langlois"
          ],
          "dureeSeance": 30,
          "mention": "Avant-première",
          "idCategorie": 3383,
          "idEvenement": 30908,
          "typeEvenement": 13,
          "idFilm": 154849,
          "titre": "Ma vie, ma gueule",
          "realisateurs": "Sophie Fillières",
          "annee": 2023,
          "pays": "France",
          "duree": 99,
          "version": "",
          "format": "DCP",
          "textes": []
        }
      ],
      "textes": []
    }
  ],
  "textes": [],
  "info": {}
}