[
  {
    "idCategorie": 3273,
    "typeEvenement": 13,
    "idEvenement": 30071,
    "idSeance": 131013,
    "dateHeure": "2024-08-29T20:00:00",
    "idSalle": [
      "HL",
      "Henri Langlois"
    ],
    "dureeSeance": 30,
    "typeSeance": 44,
    "items": [
      {
        "idFilm": 48687,
        "ordre": 1
      }
    ],
    "mention": "Ouverture de la rétrospective"
  },
  {
    "idCategorie": 3273,
    "typeEvenement": 13,
    "idEvenement": 30072,
    "idSeance": 133617,
    "dateHeure": "2024-08-31T14:30:00",
    "idSalle": [
      "HL",
      "Henri Langlois"
    ],
    "dureeSeance": 30,
    "items": [
      {
        "idFilm": 48679,
        "ordre": 1,
        "idSeance": 133617,
        "idCopie": 3865,
        "duree": 165,
        "version": "INT. FR.",
        "format": "DCP"
      }
    ]
  },
  {
    "idCategorie": 3273,
    "typeEvenement": 13,
    "idEvenement": 30068,
    "idSeance": 133614,
    "dateHeure": "2024-08-31T19:45:00",
    "idSalle": [
      "GF",
      "Georges Franju"
    ],
    "dureeSeance": 30,
    "items": [
      {
        "idFilm": 48688,
        "ordre": 1
      }
    ]
  },
  {
    "idCategorie": 3273,
    "typeEvenement": 13,
    "idEvenement": 30040,
    "idSeance": 133615,
    "dateHeure": "2024-09-01T20:15:00",
    "idSalle": [
      "GF",
      "Georges Franju"
    ],
    "dureeSeance": 30,
    "items": [
      {
        "idFilm": 48682,
        "ordre": 1
      }
    ]
  }
]