<?xml version="1.0" encoding="UTF-8"?><cycle title="Darren Aronofsky"><enTete><xTitreCycle>Darren Aronofsky&#xA;</xTitreCycle><xDatesCycle>2 - 5 avril 2025&#xA;</xDatesCycle></enTete><sousCycle title="Les films"><film title="Black Swan"><xTitre_First>Black Swan&#xA;</xTitre_First><xRealisateurs>Darren Aronofsky&#xA;</xRealisateurs><xInfosTechniques>États-Unis. 2009&#xA;</xInfosTechniques><xGenerique>Avec Natalie&#xA0;Portman, Mila&#xA0;Kunis, Vincent&#xA0;Cassel.&#xA;</xGenerique><xInfosSeance>Sa 05 avr 14h30&#x202F;-&#x202F;HL&#xA;</xInfosSeance></film><film title="Requiem for a Dream"><xTitre>Requiem for a Dream&#xA;</xTitre><xRealisateurs>Darren Aronofsky&#xA;</xRealisateurs><xInfosTechniques>États-Unis. 1999. 102’&#xA;</xInfosTechniques><xInfosSeance>Me 02 avr 20h00&#x202F;-&#x202F;HL&#xA0;<xMention>Ouverture de la rétrospective&#xA;</xMention></xInfosSeance></film></sousCycle></cycle>